
[
    {
        "img" : "test_q1.png",
        "question" : "Test question 1",
        "answers" : [
            {"answer": "Correct", "correct": true},
            {"answer": "Wrong 1", "correct": false},
            {"answer": "Wrong 2", "correct": false},
            {"answer": "Wrong 3", "correct": false}
        ]
    },
    {
        "img" : "test_q2.png",
        "question" : "Test question 2",
        "answers" : [
            {"answer": "Correct", "correct": true},
            {"answer": "Wrong 1", "correct": false},
            {"answer": "Wrong 2", "correct": false},
            {"answer": "Wrong 3", "correct": false}
        ]
    }
]
